spreadshequal/__init__.py
spreadshequal-0.0.1.dist-info/LICENSE
spreadshequal-0.0.1.dist-info/METADATA
spreadshequal-0.0.1.dist-info/WHEEL
spreadshequal-0.0.1.dist-info/entry_points.txt
spreadshequal-0.0.1.dist-info/top_level.txt
spreadshequal-0.0.1.dist-info/RECORD
