Metadata-Version: 2.1
Name: spreadshequal
Version: 0.0.1
Summary: Are those two .xlsx files as identical as they look?
Author-email: Charles Turner <charlesturner0987@gmail.com>
License: MIT License
Project-URL: homepage, https://github.com/charles-turner-1/spreadshequal
Classifier: License :: OSI Approved :: MIT License
Classifier: Programming Language :: Python :: 3
License-File: LICENSE
Requires-Dist: pandas >=1.3
Provides-Extra: dev
Requires-Dist: pytest >=3.7 ; extra == 'dev'
